ethhelper/__init__.py
ethhelper/connectors/__init__.py
ethhelper/connectors/http/__init__.py
ethhelper/connectors/http/base.py
ethhelper/connectors/http/custom.py
ethhelper/connectors/http/eth.py
ethhelper/connectors/http/graphql.py
ethhelper/connectors/http/net.py
ethhelper/connectors/http/txpool.py
ethhelper/connectors/ws/__init__.py
ethhelper/connectors/ws/base.py
ethhelper/connectors/ws/block.py
ethhelper/datatypes/__init__.py
ethhelper/datatypes/base.py
ethhelper/datatypes/eth.py
ethhelper/datatypes/geth.py
ethhelper/datatypes/txpool.py
ethhelper/py.typed
ethhelper/types.py
ethhelper/utils/__init__.py
ethhelper/utils/convert.py
ethhelper/utils/json.py
ethhelper-0.4.3.dist-info/WHEEL
ethhelper-0.4.3.dist-info/LICENSE
ethhelper-0.4.3.dist-info/METADATA
ethhelper-0.4.3.dist-info/RECORD
