Metadata-Version: 2.1
Name: ethhelper
Version: 0.4.3
Summary: Asynchronous Geth node connection encapsulation based on httpx, websockets and web3.py. Geth node and Ethereum type extension based on pydantic.
Home-page: https://github.com/XiaoHuiHui233/ETHHelper
License: Apache-2.0
Keywords: ethereum,asyncio,geth,pydantic
Author: XiaoHuiHui233
Author-email: 1025184872@qq.com
Requires-Python: >=3.10,<4.0
Classifier: License :: OSI Approved :: Apache Software License
Classifier: Programming Language :: Python :: 3
Classifier: Programming Language :: Python :: 3.10
Classifier: Programming Language :: Python :: 3.11
Requires-Dist: eth-typing (>=3.3.0,<4.0.0)
Requires-Dist: httpx (>=0.23.3,<0.24.0)
Requires-Dist: orjson (>=3.8.12,<4.0.0)
Requires-Dist: pydantic (>=1.10.7,<2.0.0)
Requires-Dist: web3 (>=6.4.0,<7.0.0)
Requires-Dist: websockets (>=10.4,<11.0)
Project-URL: Repository, https://github.com/XiaoHuiHui233/ETHHelper
